fib.py
fibonacci2283371488124-0.1.dist-info/METADATA
fibonacci2283371488124-0.1.dist-info/WHEEL
fibonacci2283371488124-0.1.dist-info/entry_points.txt
fibonacci2283371488124-0.1.dist-info/top_level.txt
fibonacci2283371488124-0.1.dist-info/RECORD
